django_excel_report/__init__.py
django_excel_report/error.py
django_excel_report/report.py
django_excel_report/writer/__init__.py
django_excel_report/writer/accessors.py
django_excel_report/writer/acessors_builder.py
django_excel_report/writer/get_queryset_builder.py
django_excel_report/writer/report_meta.py
django_excel_report/writer/writer.py
django_excel_report-0.0.6.dist-info/LICENSE
django_excel_report-0.0.6.dist-info/METADATA
django_excel_report-0.0.6.dist-info/WHEEL
django_excel_report-0.0.6.dist-info/top_level.txt
django_excel_report-0.0.6.dist-info/RECORD
