Metadata-Version: 2.1
Name: django-excel-report
Version: 0.0.6
Summary: Simplify excel reports from django apps
Author: Boris Alekseev
Author-email: i.borisalekseev@gmail.com
Maintainer: 
Maintainer-email: 
License: MIT
Project-URL: Source, https://github.com/dichem/django-excel-report
Keywords: django excel
Classifier: Development Status :: 3 - Alpha
Classifier: License :: OSI Approved :: MIT License
Classifier: Programming Language :: Python :: 3
Classifier: Programming Language :: Python :: 3.7
Classifier: Programming Language :: Python :: 3.8
Classifier: Programming Language :: Python :: 3.9
Classifier: Programming Language :: Python :: 3.10
Requires-Python: >=3.7
License-File: LICENSE
Requires-Dist: XlsxWriter (~=3.0.0)
